bidxx/__init__.py
bidxx/admin.py
bidxx/apps.py
bidxx/models.py
bidxx/tests.py
bidxx/urls.py
bidxx/views.py
bidxx-0.9.0.dist-info/LICENCE.txt
bidxx-0.9.0.dist-info/METADATA
bidxx-0.9.0.dist-info/WHEEL
bidxx-0.9.0.dist-info/top_level.txt
bidxx-0.9.0.dist-info/RECORD
