Metadata-Version: 2.1
Name: bidxx
Version: 0.9.0
Summary: Describe your package in one sentence
Home-page: https://github.com/you/your_package
Author: SHARASHELL TECHNOLOGY LIMITED
Author-email: sharashelltechnologyltd@gmail.com
License: OSI Approved :: MIT
Classifier: Programming Language :: Python :: 3
Classifier: License :: OSI Approved :: MIT License
Classifier: Operating System :: OS Independent
License-File: LICENCE.txt
